{"publisher":"文化部","publishNo":"文藝字第1043034437號","publishDate":"2015-12-30","summary":"有關臺中市政府文化局函詢「臺中市快捷巴士  （ BRT）藍線優先路段及臺中市快捷巴士  \n（ BRT）藍線延伸第一期路段建置計畫」公共藝術設置計畫經費返還疑義乙案","content":"一、復貴局 104年12月10日中市文視字第1040028452號函。\n 二、依「公共藝術設置辦法」第 5條第 2項規定：「公共藝術設置計畫預算逾新臺幣30萬\n   元者，興辦機關經審議會審核同意後，得將公共藝術經費之全部或部分交由該基地所\n   在地之直轄市、縣（市）政府統籌辦理公共藝術有關事宜。」\n 三、另依「臺中市推動公共藝術設置自治條例」第 6條規定：「興辦機關得依公共藝術設\n   置辦法第 5條規定，將公共藝術設置經費，繳入臺中市公共藝術基金，由本府統籌辦\n   理公共藝術有關事宜。」，又「臺中市公共藝術基金收支保管及運用辦法」第 2條規\n   定：「臺中市公共藝術基金……主管機關為臺中市政府文化局。」\n 四、綜上，旨案公共藝術經費既經繳入「臺中市公共藝術基金」，由臺中市政府統籌辦理\n   公共藝術事宜，是否同意基金主管機關臺中市政府文化局返還臺中市政府交通局已繳\n   納之經費，宜由貴府依權責卓處，本部予以尊重。"}
