{"publisher":"財團法人中小企業信用保證基金","publishNo":"(103)保證規劃字第6198999號函","publishDate":"2014-03-14","summary":"為配合業務發展之需要，玆調整財團法人中小企業信用保證基金「協助中小企業參與公共建設」之保證措施如說明二","content":"主旨：為配合業務發展之需要，玆調整本基金「協助中小企業參與公共建設」之保證措施如\n   說明二，請 查照，並惠轉 貴屬各授信單位配合辦理。\n說明：\n 一、依據經濟部 103年 3月 4日經授企字第 10320390610號函及本基金103 年 2月19日第\n   13屆董事會第 5次董事會議決議辦理。\n 二、本基金前於 101年12月24日（ 101）保證規劃字第 6183747號函檢送賡續實施之「促\n   進就業融資保證專案」，其中「協助中小企業參與公共建設」之保證措施，係額外增\n   加信用保證融資額度 1億元（以下簡稱「外加融資額度」），不受本基金對同一企業\n   保證融資總額度上限之限制。本項措施係於97年12月15日開辦，以配合當時金融海嘯\n   之融資環境，實施迄今已有五年以上，基於目前國內景氣尚屬穩定、本基金保證能量\n   狀況及保證資源分配合理性之考量，並顧及企業資金調度及金融機構作業之配合，爰\n   規劃以漸進式分二階段逐步調整之原則，辦理至 104年底止：\n  （一）第一階段：自 103年 7月 1日至 103年12月31日「外加融資額度」改為 6千萬元\n     。\n  （二）第二階段：自 104年 1月 1日至 104年12月31日「外加融資額度」改為 3千萬元\n     。\n正本：各簽約金融機構\n副本：經濟部中小企業處、金融監督管理委員會銀行局、中央銀行業務局、中央銀行金融業\n   務檢查處、中華民國銀行商業同業公會全國聯合會"}
