{"publisher":"行政院人事行政總處","publishNo":"總處給字第1090038503號E-mail回函","publishDate":"2020-08-07","summary":"調往不同級別偏遠地區後，地域加給年資加成得否合併計算","content":"一、查「各機關學校公教員工地域加給表」附則 4規定：「本表自79年 7月 1日起算，每服\n  務當地時間滿 1年，按俸額加 2％計給，最高以本表所列各級最高比例為限；其服務於\n  本表各山僻、離島地區之年資得合併採計。」復查原行政院人事行政局92年 5月30日局\n  給字第0920054040號書函略以，如原服務於第 1級偏遠地區未達該級次所訂年資加成之\n  上限者，於調任第 2（ 3、 4）級山僻、離島地區服務時，得合併採計服務年資。至原\n  服務於第 1級偏遠地區並支給年資加成之上限，其於調任第 2級山僻、離島地區服務時\n  ，應以所支給第 1級高限（即加成 10%）為基準，按每服務「當地」時間滿 1年，俸額\n  加2%計給，最高以該級最高加成比例為限。\n二、本案所詢曾服務於第 3級離島地區（年資加成上限為 30%）、第 1級離島地區者（年資\n  加成上限為 10%），嗣後再服務於第 3級離島地區時，其年資加成之採計為以第 1級離\n  島地區地域加給支給有案年資之加成比例最高得採計至 10%為基準，加計原第 3級離島\n  地區之年資加成比例併計至第 3級離島地區之年資加成上限為止。"}
