{"publisher":"行政院農業委員會","publishNo":"農授金字第1035074224C號","publishDate":"2014-12-30","summary":"有關重設信用部之授信業務範圍案","content":"主旨：有關重設信用部之授信業務範圍案，請依說明辦理，請查照轉知。說明：\n 一、開業初期限辦理以下業務：\n  （一）政策性農業專案貸款。\n  （二）存單質借。\n  （三）對直轄市、縣（市）政府、鄉（鎮、市）公所放款。\n  （四） 100萬元以下之小額貸款。\n  （五）會員（含贊助會員）房屋購置及修繕貸款。\n  （六）公庫透支。\n 二、同時符合已核准通過參加存款保險、逾放比率 1％以下、淨值占風險性資產比率10％\n   以上、淨值 3千萬元以上等條件時，得依信用部開業時間長短，報經貴府層轉本會核\n   准辦理下列業務：\n  （一）開業滿 1年後，會員（含贊助會員）授信業務比照一般農漁會信用部辦理。\n  （二）開業滿 2年後，得辦理非會員以同一直轄市、縣（市）及毗鄰二鄉、鎮、市、區\n     內之住宅為擔保之放款。\n  （三）開業滿 3年後，非會員授信業務比照一般農漁會信用部辦理。三、開業滿 5年後\n     ，符合逾放比率 1％以下、淨值占風險性資產比率 8％以上、淨值 3千萬元以上\n     等財業務條件，得報經貴府層轉本會核准辦理內部融資，其額度為法定限額二分\n     之一。\n 四、本會 101年 2月23日農授金字第1015070138號函即日起停止適用。正本：臺中市政府\n   、臺南市政府、高雄市政府、桃園市政府、新竹縣政府、彰化縣政府、雲林縣政府、\n   屏東縣政府\n副本：金融監督管理委員會檢查局、中央存款保險股份有限公司、全國農業金庫股份有限公\n   司、中華民國農會"}
