{"publisher":"勞動部","publishNo":"勞動發管字第1090516660號令","publishDate":"2020-10-20","summary":"令釋「外國人從事就業服務法第四十六條第一項第八款至第十一款工作資格\r\n及審查標準」相關規定中，雇主申請初次招募外國人或引進外國人之人數，\r\n經計算結果有小數點者，以小數點後第一位四捨五入計算","content":"全文內容：核釋「外國人從事就業服務法第四十六條第一項第八款至第十一款工作資\r\n          格及審查標準」第九條、第十四條之一、第十四條之二、第十四條之三、\r\n          第十四條之四、第十四條之五、第十四條之八、第十四條之十、第十四條\r\n          之十二、第十五條之五、第十六條之四、第十八條、第十八條之一、第十\r\n          八條之二、第十八條之三、第十九條之二、第十九條之三及第十九條之十\r\n          二規定，雇主申請初次招募外國人或引進外國人之人數，經計算結果有小\r\n          數點者，以小數點後第一位四捨五入計算，並自即日生效。\r\n          本部（改制前行政院勞工委員會）中華民國一百零二年五月九日勞職管字\r\n          第一○二○五○三八七一號令，自即日起廢止。","comment":"1.依本筆資料，原行政院勞工委員會民國 102  年 5  月 9  日勞職管字\r\n  第 1020503871 號令，自即日起廢止。\r\n2.本筆資料，依據勞動部民國 111  年 6  月 28 日勞動發管字第 11105\r\n  099981  號令，自即日起廢止。"}
