{"publisher":"勞動部","publishNo":"勞動發管字第1040516536號令","publishDate":"2016-01-20","summary":"令釋符合私立就業服務機構許可及管理辦法第 5  條第 2  項所稱同等學\r\n力資格之情形，並自即日生效","content":"全文內容：核釋私立就業服務機構許可及管理辦法第五條第二項所稱同等學力資格，\r\n          指符合下列情形之一者：\r\n      （一）依自學進修學力鑑定考試辦法規定取得專科學校畢業程度學力鑑定通過\r\n            證書。\r\n      （二）依自學進修高級中等教育學力鑑定考試辦法規定取得普通型高級中等學\r\n            校或技術型高級中等學校畢業程度學力鑑定通過證書。\r\n      （三）具有入學大學同等學力認定標準所列同等學力規定之證明文件。\r\n      （四）具有入學專科學校同等學力認定標準所列報考二年制專科學校一年級新\r\n            生入學考試同等學力規定之證明文件。\r\n          本解釋令自即日生效。\r\n          本部（改制前行政院勞工委員會）中華民國九十八年十一月十日勞職管字\r\n          第○九八○五○三三○八號令，自即日廢止。","comment":"1.依本筆資料，原行政院勞工委員會民國 98 年 11 月 10 日勞職管字 0\r\n  980503308 號令，廢止。"}
