{"publisher":"臺灣期貨交易所股份有限公司","publishNo":"臺期輔字第10500024891號函","publishDate":"2016-08-22","summary":"公告期貨商富邦期貨股份有限公司期貨自營業務申報開業乙案","content":"主旨：公告期貨商富邦期貨股份有限公司期貨自營業務申報開業乙案。\n說明：\n  一、依據期貨商管理規則第4條第1項第1款、本公司業務規則第14條第1\n      項第1款規定及該公司105年8月8日富期自字第1050000209號函辦理\n      。\n  二、富邦期貨股份有限公司期貨自營業務，訂於105年8月26日開始營業\n      ，其期貨商代號、營業處所地址等有關資料如附件。\n正本：各期貨商\n副本：財政部臺北市國稅局、中華民國期貨業商業同業公會、中華民國證\n      券商業同業公會、臺灣證券交易所股份有限公司、財團法人中華民\n      國證券櫃檯買賣中心、臺灣集中保管結算所股份有限公司、交易部\n      、結算部、監視部、資訊作業部、管理部、本公司網站、各資訊公\n      司"}
