{"publisher":"臺灣證券交易所股份有限公司","publishNo":"臺證輔字第1080008517號函","publishDate":"2019-05-23","summary":"修正「證券商內部控制制度標準規範」及「期貨商經營證券交易輔助業務\n內部控制制度標準規範」","content":"主旨：修正「證券商內部控制制度標準規範」及「期貨商經營證券交易輔\n      助業務內部控制制度標準規範」，自即日起實施，請查照。\n說明：\n  一、依據金融監督管理委員會 108年 5月17日金管證券字第1080306635\n      號函辦理。\n  二、旨揭修正案，業經本公司、財團法人中華民國證券櫃檯買賣中心、\n      中華民國證券商業同業公會及臺灣集中保管結算所股份有限公司共\n      同修正，並報奉主管機關同意備查。相關修正內容已置於本公司網\n      站（ www.twse.com.tw→「產品與服務」→「證券商服務」→「券\n      商輔導部」→「文件下載」），請自行下載，並即依修正內容修正\n      貴公司內部控制制度及落實執行，至遲應於 108年 6月15日開始執\n      行（內部控制制度須經董事會通過，如未及於 108年 6月15日前召\n      開董事會通過，亦應儘速召集董事會追認，外國證券商在臺分支機\n      構得由在臺分支機構負責人書面同意替代之）。\n  三、除經通知或其他法令另有規定外，證券商及證券交易輔助人無須將\n      內部控制制度之訂定或修正內容，申報本公司等證券相關機構，惟\n      應將內部控制制度之訂定或修正內容及董事會通過之議事錄等資料\n      妥善保存，並依主管機關或本公司等證券相關機構通知，即時提供\n      查核。\n  四、惠請財團法人中華民國證券櫃檯買賣中心及中華民國證券商業同業\n      公會分別將本函轉知未與本公司簽訂市場契約之證券商。\n正本：各證券商、各期貨商\n副本：金融監督管理委員會證券期貨局、金融監督管理委員會檢查局、財\n      團法人中華民國證券櫃檯買賣中心、中華民國證券商業同業公會、\n      臺灣集中保管結算所股份有限公司、臺灣期貨交易所股份有限公司\n      、法源資訊股份有限公司、植根國際資訊股份有限公司、國際通商\n      法律事務所、博仲法律事務所、本公司交易部、上市二部、電腦規\n      劃部、資訊服務部、秘書部、券商輔導部"}
