{"publisher":"金融監督管理委員會","publishNo":"金管證投字第1060030890號令","publishDate":"2017-09-15","summary":"證券投資信託事業或證券投資顧問事業將全權委託投資帳戶之後臺帳務處\n理作業辦理應遵行事項","content":"一、證券投資信託事業或證券投資顧問事業將全權委託投資帳戶之後臺帳\n    務處理作業（包括全權委託投資帳戶之資產評價、資產價值計算及會\n    計處理等）委託專業機構（下稱受託機構）辦理，應遵行下列事項：\n  （一）證券投資信託事業或證券投資顧問事業應與受託機構訂定書面契\n        約，載明委任事項、期間、受託機構權責及前揭事業之監督責任\n        。\n  （二）證券投資信託事業或證券投資顧問事業應具備隨時有效監督受託\n        機構之機制及能力，其責任與義務並未因委外行為而得以免除，\n        仍須對全權委託投資契約客戶負責；並應於內部控制制度中訂定\n        全權委託投資帳戶後臺帳務處理委外作業之監控管理措施，提經\n        董事會通過。\n  （三）受託機構應對於受委任業務具備專業能力，並依法得辦理與全權\n        委託投資帳戶後臺帳務處理作業相關之代理業務。\n  （四）全權委託投資契約客戶應以書面同意證券投資信託事業或證券投\n        資顧問事業得委託受託機構辦理全權委託投資帳戶後臺帳務處理\n        作業。\n二、本令自即日生效。\n正本：貼金融監督管理委員會公告欄、金融監督管理委員會證券期貨局公\n      告欄\n副本：行政院法規會、金融監督管理委員會（法律事務處、資訊服務處）\n      、金融監督管理委員會檢查局、金融監督管理委員會銀行局、中華\n      民國證券投資信託暨顧問商業同業公會、中華民國信託業商業同業\n      公會、中華民國銀行業商業同業公會、法源資訊股份有限公司、植\n      根國際資訊股份有限公司"}
