{"publisher":"金融監督管理委員會","publishNo":"金管保壽字第10410933850號函","publishDate":"2015-10-06","summary":"所詢「保險業負責人應具備資格條件準則」第 3條第 1項第13款規定之適用疑義乙案","content":"主旨：所詢「保險業負責人應具備資格條件準則」第 3條第 1項第13款規定之適用疑義乙案\r\n      ，復如說明，請查照。\r\n說明：\r\n  一、依據本會保險局案陳貴公司 104年 8月11日國壽字第1040081005號函辦理。\r\n  二、查旨揭條款之立法目的，係在避免保險業負責人同時擔任其他金融機構負責人時所生\r\n      之利益衝突及競業禁止。依外國法律組織設立而未在我國境內設立分支機構之國外或\r\n      大陸地區之金融機構，因在臺並無營業，尚無上揭立法時之考量情形，合先敘明。\r\n  三、承上，旨揭條款規定「擔任其他保險業、金融控股公司、銀行、信託公司、信用合作\r\n      社、農（漁）會信用部、票券金融公司、證券公司、證券金融公司、證券投資信託公\r\n      司、證券投資顧問公司或期貨商之負責人者。」所稱之其他保險業等金融機構，尚不\r\n      及於依外國法律組織設立而未在我國境內設立分支機構之國外或大陸地區之金融機構\r\n      。\r\n正本：國○人壽保險股份有限公司（代表人蔡○圖）\r\n副本：中華民國人壽保險商業同業公會（代表人許○博）、中華民國產物保險商業同業公會\r\n      （代表人戴○祥）、財團法人保險事業發展中心（代表人曾○瓊）、金融監督管理委\r\n      員會檢查局、保險局"}
