{"publisher":"金融監督管理委員會","publishNo":"金管證發字第11103828171號函","publishDate":"2022-08-11","summary":"前財政部證券暨期貨管理委員會八十七年十二月十日（八七）台財證（一\n）第０三五三四號函及八十八年九月二十七日（八八）台財證（一）第四\n七六九三號公告，自即日停止適用\n（原財政部證券暨期貨管理委員會 87.12.10.  （87）臺財證（一）字第\n03534號函停止適用）\n（原財政部證券暨期貨管理委員會 88.09.27.  （88）臺財證（一）字第\n47693號公告停止適用）","content":"主旨：前財政部證券暨期貨管理委員會八十七年十二月十日（八七）台財\n      證（一）第０三五三四號函及八十八年九月二十七日（八八）台財\n      證（一）第四七六九三號公告，自即日停止適用，請查照。\n正本：貼金融監督管理委員會公告欄、貼證券期貨局公告欄\n副本：行政院法規會、本會法律事務處、資訊服務處、檢查局、臺灣證券\n      交易所股份有限公司（代表人林○銘先生）、財團法人中華民國證\n      券櫃檯買賣中心（代表人陳○誠先生）、植根國際資訊股份有限公\n      司（代表人吳○子女士）、法源資訊股份有限公司（代表人王○薇\n      女士）、臺灣集中保管結算所股份有限公司（代表人朱○強先生）\n      、財團法人中華民國證券暨期貨市場發展基金會（代表人林○輝先\n      生）、社團法人中華民國會計師公會全國聯合會（代表人黃○睿先\n      生）、中華民國證券投資信託暨顧問商業同業公會（代表人劉○聖\n      先生）、中華民國期貨業商業同業公會（代表人陳○君女士）、中\n      華民國證券商業同業公會（代表人陳○宏先生）"}
