{"publisher":"金融監督管理委員會","publishNo":"金管證投字第1080301317號令","publishDate":"2019-01-25","summary":"放寬「ETF連結基金」投資於ETF（主基金）可以超過該主基金已發行受益\n權單位總數之10％\n（原金融監督管理委員會 107.10.17  金管證投字第1070335922號令廢止\n）\n\n不再援用：依據金融監督管理委員會 108.04.30.  金管證投字第1080312\n          172號令自即日廢止","content":"一、依據證券投資信託基金管理辦法第十條第一項及第二十三條第九款規\n    定辦理。\n二、證券投資信託事業已經理指數股票型證券投資信託基金（下稱 ETF）\n    者，得向本會申請核准募集單一連結所經理 ETF（下稱主基金）之連\n    結基金（下稱ETF連結基金）。\n三、證券投資信託事業運用 ETF連結基金，為符合投資策略所需，得不受\n    證券投資信託基金管理辦法第十條第一項第十一款本文及第十二款規\n    定之限制，並應符合下列規定：\n  （一）所投資之主基金以國內成分證券 ETF為限，且應達基金淨資產價\n        值之百分之九十以上。\n  （二）應於基金名稱中標明「連結」字樣及所投資之主基金名稱。\n四、本令自即日生效；本會中華民國一百零七年十月十七日金管證投字第\n    一０七０三三五九二二號令，自即日廢止。\n正本：貼金融監督管理委員會公告欄、金融監督管理委員會證券期貨局公\n      告欄\n副本：行政院法規會、金融監督管理委員會（法律事務處、資訊服務處）\n      、金融監督管理委員會檢查局、中華民國證券投資信託暨顧問商業\n      同業公會、法源資訊股份有限公司、植根國際資訊股份有限公司\n〔依金融監督管理委員會 108.04.30.  金管證投字第 1080312172號令發\n布，自108年4月30日廢止〕"}
