{"publisher":"內政部營建署","publishNo":"營署建管字第1032904856號函","publishDate":"2014-03-19","summary":"有關農業發展條例89年修正施行前，以10公里範圍內未毗鄰農地合併檢討興建農舍領有使用\r\n執照辦理解除套繪管制事宜 1案","content":"主旨：民眾陳為，有關農業發展條例89年修正施行前，以10公里範圍內未毗鄰農地合併檢討\r\n      興建農舍領有使用執照辦理解除套繪管制事宜 1案，請查照。\r\n說明：\r\n  一、依據蘇○雲君 103年未具日期申請書（如附件）辦理。\r\n  二、依據農業用地興建農舍辦法（以下簡稱本辦法）第12條第 3項規定：「已申請興建農\r\n      舍領有使用執照之農業用地經套繪管制，除符合下列情形之一者外，不得解除：一、\r\n      農舍坐落之農業用地已變更為非農業用地。二、非屬農舍坐落之農業用地已變更為非\r\n      農業用地。三、農舍用地面積與農業用地面積比例符合法令規定，經依變更使用執照\r\n      程序申請解除套繪管制後，該農業用地面積仍達0.25公頃以上。」次按「前以10公里\r\n      範圍內未毗鄰農地合併檢討興建農舍或因農地重劃分割等致無法合併為一筆者，得以\r\n      農舍及其符合規定比例之多筆農地套繪列管；其餘超出規定比例之農地，得依變更使\r\n      用執照程序申解除套繪列管。」本署 101年 9月20日營署建管字第1010055419號函說\r\n      明三已有明示，該函釋依本辦法第12條第 3項規定，其符合規定比例之多筆農地面積\r\n      應達0.25公頃以上，其餘超出規定比例之農地，得依變更使用執照程序申請解除套繪\r\n      列管。至本案位於貴府轄內之已申請興建農舍之農業用地辦理解除套繪管制事宜，因\r\n      涉個案事實認定，係屬貴管，移請查明卓處逕復。\r\n正本：南投縣政府\r\n副本：蘇○雲君、本署建築管理組"}
