{"publisher":"內政部","publishNo":"內授營建管字第1030071581號函","publishDate":"2014-02-06","summary":"關於領有電匠考驗合格證明文件之人員得否參加建築物公共安全檢查專業檢查人認可資格講\r\n習課程","content":"  一、按建築法第77條第 3項規定：「供公眾使用之建築物，應由建築物所有權人、使用人\r\n      定期委託中央主管建築機關認可之專業檢查機構或人員檢查簽證，其檢查結果應向當\r\n      地主管建築機關申報。非供公眾使用之建築物，經內政部認有必要時亦同。」；本部\r\n      為執行前揭條文所稱專業檢查機構、人員認可之相關事項，訂有「建築物公共安全檢\r\n      查專業機構及專業檢查人認可要點」（下稱本要點）憑辦。又本部認可之設備安全類\r\n      專業檢查人應具有「1.依法登記開業之建築師。2.依法登記開業之土木工程技師、結\r\n      構工程技師、電機工程技師、機械工程技師、冷凍空調工程技師及消防設備師，並參\r\n      加本部主辦或委託相關機關、團體舉辦講習訓練達 7小時以上，經測驗合格取得結業\r\n      證明文件者。3.領有昇降機裝修、機械停車設備裝修、室內配線（屋內線路裝修）、\r\n      冷凍空調裝修等相關甲級或乙級技術士證，並參加本部主辦或委託相關機關、團體舉\r\n      辦講習訓練達21小時以上，經測驗合格取得結業證明文件者。」等資格之 1，為該要\r\n      點第 3點第 1項第 2款明示在案。\r\n  二、本案據經濟部能源局前揭函示，略以：「查行政院98年修正發布之『技術上與公共安\r\n      全有關事業機構應僱用技術士之業別及比率（人數）一覽表』規定，其中有關用電設\r\n      備檢修維護業之僱用人員，甲、乙種電匠證照效力分別比照室內配線乙、丙級技術士\r\n      證。…復查『電器承裝業管理規則』明定，甲、乙級承裝業應僱用之電氣技術人員中\r\n      ，室內配線、工業配線、配電線路裝修、配電電纜裝修、輸電地下電纜裝修、輸電架\r\n      空線路裝修、變壓器裝修、變電設備裝修或用電設備檢驗職類之乙級技術士與甲種電\r\n      匠係屬同目資格。…再者，『專任電氣技術人員及用電設備檢驗維護業管理規則』明\r\n      定，甲種電匠與室內配線、工業配線、變電線路裝修或用電設備檢驗職類之乙級技術\r\n      士同屬中級電氣技術人員資格。…於上述執業範圍內，甲種電匠與乙級技術士僅具同\r\n      等任用資格，兩者並無可直接替換關係。」是以，經濟部96年3 月21日修正發布「電\r\n      業法」及96年 7月19日廢止「電匠考驗規則」前領得甲種電匠考驗合格證明文件之人\r\n      員，除受僱於用電設備檢修維護業、用電設備檢驗維護業及電器承裝業時，得比照室\r\n      內配線乙級技術士資格條件外，兩者並無可直接替換關係。又行政院勞工委員會96年\r\n       6月29日勞中三字第0960301770號公告停止辦理「 00701室內配線─甲種電匠」一試\r\n      兩證技能檢定前，受檢定人員通過測試即可同時取得室內配線技術士及甲種電匠資格\r\n      。準此，領得甲種電匠考驗合格證明文件之人員不得直接視同本要點第 3點第 1項第\r\n       2款第 3目列舉之室內配線（屋內線路裝修）乙級技術士資格條件，參加建築物公共\r\n      安全檢查專業檢查人認可資格講習課程。"}
