{"publisher":"法務部","publishNo":"法律字第10403500050號函","publishDate":"2015-01-08","summary":"有關共有物權利行使疑義","content":"主旨：有關共有物權利行使疑義一案，復如說明二至四，請查照參考。\r\n說明：\r\n  一、復貴部 103年11月13日經商字第 10300700170號函。\r\n  二、按民法第 820條規定：「共有物之管理，除契約另有約定外，應以共有人過半數及其\r\n      應有部分合計過半數之同意行之。但其應有部分合計逾三分之二者，其人數不予計算\r\n      。……」其中所稱共有物之管理，包括對分別共有物之保存、改良、利用（例如：出\r\n      租共有物）等行為，除契約另有訂定外（例如：共有物之分管契約），應以共有人過\r\n      半數及其應有部分合計過半數之同意行之；但其應有部分合計逾三分之二者，其人數\r\n      不予計算，民法第 820條第 1項已就分別共有物之管理定有明文。至於公同共有物之\r\n      管理，依民法第 828條第 1項規定，須先依其公同關係所由成立之法律、法律行為或\r\n      習慣定其權利義務之行使；如無特別規定其權利義務之行使方法，當事人亦無分管契\r\n      約時，再依民法第 828條第 2項規定「準用」民法第820 條第 1項規定；最後方適用\r\n      民法第 828條第 3項規定，依公同共有人全體同意之方式（本部98年10月 1日法律字\r\n      第0980032730號函、本部 103年11月 3日法律決字第 10300204530號函參照），與分\r\n      別共有物之管理依據有所不同，應予辨明。\r\n  三、次按共有人中之一人或數人，未依前開所述多數決之方式，擅將共有物出租予他人之\r\n      債權行為，僅係對於他共有人不生效力（最高法院96年度台上字第 920號民事判決意\r\n      旨參照）。換言之，分別共有人將共有物出租他人者，無論是否符合前開多數決要件\r\n      ，租賃契約於訂立契約之當事人間仍係有效成立（最高法院76年度台上字第2803號民\r\n      事判決意旨、本部 101年11月15日法律字第 10100135930號函參照）。\r\n  四、本件因來函所述仍有未明，如尚有適用法律之疑義，仍請依中央行政機關法制作業應\r\n      注意事項第18點、第19點規定，先洽請貴部法制單位表示意見，再依上開規定敘明各\r\n      種疑義、其得失分析，以及擬採之見解及其理由，來函憑辦，俾利釋復。\r\n正本：經濟部\r\n副本：本部資訊處（第 1類）、本部法律事務司（ 4份）"}
