{"publisher":"法務部","publishNo":"法律字第11103513630號","publishDate":"2022-11-02","summary":"有關財團法人法董事連任之疑義乙案","content":"主旨：有關財團法人法董事連任之疑義乙案，復如說明二，請查照。\n說明：\n一、復貴部111年9月16日文綜字第11130249972號函。\n二、按財團法人法（下稱本法）第40條第1項及第4項規定：「民間捐助之\n  財團法人董事之任期，每屆不得逾 4年；期滿連任之董事，不得逾改\n  選董事總人數 5分之4（第1項）。…。董事於任期屆滿前，因辭職、\n  死亡，或因故無法執行職務被解任者，得另選其他人選繼任，至原任\n  期屆滿為止（第 4項）。」規定財團法人之董事會採屆期制，並明定\n  民間捐助之財團法人董事任期及每屆期滿連任董事人數之限制，以免\n  形成萬年董事會，並符「他律法人」之性質（本條立法理由參照），\n  爰此「期滿連任之董事」應以屆期為判斷標準，即連續 2屆均曾當選\n  就任而言。從而，如民間捐助財團法人之董事於當屆任期屆滿前辭職\n  ，於次屆董事改選時仍應計入本條第 1項後段所定「期滿連任之董事\n  」（本部 108年9月16日法律字第10803511910號函參照）。至本件來\n  函所詢，因涉事實判斷，仍請參照上開說明就具體個案情形本於職權\n  審認之。"}
