{"publisher":"法務部","publishNo":"法制字第 11102505740 號","publishDate":"2022-03-29","summary":"法務部就有關「長期照顧服務機構個人資料檔案安全維護計畫實施辦法」草案之意見","content":"主    旨：有關「長期照顧服務機構個人資料檔案安全維護計畫實施辦法」草案乙案\n          ，本部意見如說明二，請查照。\n說    明：一、依貴部 111  年 2  月 18 日衛部顧字第 1111960160B  號函辦理。\n          二、本部意見如下：\n          （一）草案名稱：\n                按長期照顧服務機構（以下簡稱長照機構）由政府機關（構）設立\n                者為公立長照機構、由民間設立者為私立長照機構（長期照顧服務\n                法第 26 條第 1  項規定參照），又本草案第 3  條說明亦已載明\n                本辦法之適用對象不包括公立長照機構，則本草案名稱是否宜修正\n                為「『私立』長期照顧服務機構個人資料檔案安全維護計畫實施辦\n                法」？俾使本草案望名即知規定之範圍，建請再酌。\n          （二）草案第 3  條：\n                本條第 1  項第 1  款規定「……依長期照顧服務法『（以下簡稱\n                長服法）』……」，惟查本草案並未再次援用該法，似無簡稱必要\n                ，建請修正。\n          （三）草案第 4  條：\n                本條規定，長照機構應依本辦法規定訂定安全維護計畫，惟查本條\n                說明載以「……，爰明定長照機構訂定安全維護計畫時，應視其規\n                模、特性、保有個人資料之性質、方法及數量等事項，訂定適宜並\n                符合比例原則之計畫項目」與本條規定內容不同，建請修正；又上\n                開說明似較符合草案第 6  條規定，建請釐清定明。\n          （四）草案第 5  條：\n                1.本條說明一「……影響之層面甚『巨』……」，建請修正為「鉅\n                  」。\n                2.本條第 1  項規定，長照機構執行業務以「資通系統」蒐集、處\n                  理或利用其當事人之個人資料，且許可床數逾 2  百床者，應採\n                  取較嚴格之資訊安全措施；又依本條說明二，該「資通系統」係\n                  依資通安全管理法第 3  條第 1  款規定，用以蒐集、控制、傳\n                  輸、儲存、流通、刪除資訊或對資訊為其他處理、使用或分享之\n                  系統。既該「資通系統」之相關規定定明於資通安全管理法，則\n                  本條第 1  項所定之「資通系統」建請定明為「依資通安全管理\n                  法規定之資通系統」，或參考短期補習班個人資料檔案安全維護\n                  計畫實施辦法第 15 條第 2  項及第 3  項後段之立法方式，予\n                  以定明，俾資明確。\n          （五）草案第 9  條：\n                本條規定，長照機構將當事人個人資料為國際傳輸前，「應檢視是\n                否受中央主管機關限制」，並告知當事人擬傳輸之國家或區域，查\n                該「中央主管機關限制」依本條說明所載，即為個人資料保護法（\n                以下簡稱本法）第 21 條規定之情形，故建請參考私立兒童課後照\n                顧服務中心個人資料檔案安全維護計畫實施辦法第 9  條第 3  項\n                前段規定，修正為「應檢視是否受中央主管機關『依本法第 21 條\n                規定為國際傳輸之』限制」，俾期明確。\n正    本：衛生福利部\n副    本：本部法制司"}
