{"publisher":"考選部","publishNo":"選特四字第1030000948號函","publishDate":"2014-03-10","summary":"特種考試臺灣省及福建省基層公務人員考試及格人員，於限制轉調期限內離職後再任公職，\r\n因原分發占缺任用機關裁撤，依特種考試地方政府公務人員考試規則第 9條第 2項規定，繼\r\n續在原錄取分發區同職組各職系機關任職合併年資期滿，視同在原分發占缺任用機關服務期\r\n滿","content":"  一、查本部89年 6月14日選特四字第0890006939號書函回復銓敘部函詢有關特種考試臺灣\r\n      省及福建省基層公務人員考試及格人員於原分發占缺任用機關之限制轉調年限內辭職\r\n      ，如擬再任，因原分發占缺機關已民營化，可否放寬至性質相近之機關，視同補足原\r\n      限制轉調規定之年限疑義乙案略以，為保障本考試及格人員權益及不違反特考特用原\r\n      則下，同意本考試及格人員於原錄取分發區機關之有關職務任職，視同補足原限制轉\r\n      調規定年限。\r\n  二、前揭限制轉調疑義函釋之內容核與特種考試地方政府公務人員考試規則第 9條第 2項\r\n      規定：「前項及格人員於分發占缺之機關（構）或學校，如因業務調整而精簡、整併\r\n      、改隸、改制或裁撤，須移撥安置至其他機關（構）或學校時，繼續在原錄取分發區\r\n      同職組各職系機關任職合併年資期滿，視同在原分發占缺任用機關服務期滿。」之立\r\n      法意旨相符，爰此特種考試臺灣省及福建省基層公務人員考試及格人員於限制轉調期\r\n      限內離職後如擬再任公職，因原分發占缺任用機關裁撤，如繼續在原錄取分發區同職\r\n      組各職系機關任職合併年資期滿，視同在原分發占缺任用機關服務期滿。即得再任原\r\n      分發占缺任用以外之機關有關職務，惟以原錄取分發區所屬機關（包括縣政府、鄉（\r\n      鎮、市）公所及其所屬機關、學校，縣議會、鄉（鎮、市）民代表會）為限，至再任\r\n      職務應依公務人員任用相關法規之規定辦理。"}
